Money_counter/Money_counter.v
module money_counter (
    input wire clk,
    input wire reset,
    input wire [1:0] coin_in,    // 00: no coin, 01: 1₫, 10: 5₫, 11: 10₫
    output reg [4:0] total_amount
);
    // Định nghĩa giá trị tiền
    parameter COIN_1 = 5'd1;
    parameter COIN_5 = 5'd5;
    parameter COIN_10 = 5'd10;
    
    // SỬA: Thêm edge detection để chỉ đếm 1 lần cho mỗi coin
    reg [1:0] coin_in_prev;
    wire coin_inserted = (coin_in != 2'b00) && (coin_in_prev == 2'b00);
    
    always @(posedge clk) begin
        if (reset) begin
            total_amount <= 5'd0;
            coin_in_prev <= 2'b00;
        end
        else begin
            coin_in_prev <= coin_in;
            
            // CHỈ cộng tiền khi phát hiện EDGE (từ 00 -> coin)
            if (coin_inserted) begin
                case (coin_in)
                    2'b01: begin
                        if (total_amount <= 5'd30)
                            total_amount <= total_amount + COIN_1;
                    end
                    2'b10: begin
                        if (total_amount <= 5'd26)
                            total_amount <= total_amount + COIN_5;
                    end
                    2'b11: begin
                        if (total_amount <= 5'd21)
                            total_amount <= total_amount + COIN_10;
                    end
                endcase
            end
        end
    end
endmodule

Money_counter/Money_counter_tb.v
module money_counter_tb;
    // Testbench signals
    reg clk;
    reg reset;
    reg [1:0] coin_in;
    
    wire [4:0] total_amount;
    
    // Instantiate the money counter
    money_counter uut (
        .clk(clk),
        .reset(reset),
        .coin_in(coin_in),
        .total_amount(total_amount)
    );
    
    // Clock generation - 50MHz
    initial begin
        $dumpfile("money_counter.vcd");
        $dumpvars(0, money_counter_tb);
        clk = 0;
        forever #10 clk = ~clk; // Chu kỳ 20ns = 50MHz
    end
    
    // Task để nhập tiền với edge detection
    task insert_coin;
        input [1:0] coin_type;
        input [7:0] coin_name; // Để hiển thị tên loại tiền
        begin
            // Đảm bảo coin_in = 00 trước khi nhập
            @(posedge clk);
            coin_in = 2'b00;
            @(posedge clk);
            
            // Tạo edge từ 00 -> coin_type
            coin_in = coin_type;
            case (coin_type)
                2'b01: $display("Time %0t: Nhập đồng 1₫ - Edge detected", $time);
                2'b10: $display("Time %0t: Nhập đồng 5₫ - Edge detected", $time);
                2'b11: $display("Time %0t: Nhập đồng 10₫ - Edge detected", $time);
            endcase
            
            repeat(3) @(posedge clk); // Giữ trong 3 cycles để test
            
            // Trở về 00
            coin_in = 2'b00;
            @(posedge clk);
            $display("Time %0t: Tổng tiền hiện tại: %0d₫", $time, total_amount);
        end
    endtask
    
    // Task để test nhiều lần nhập cùng loại tiền
    task rapid_insert;
        input [1:0] coin_type;
        input integer count;
        integer i;
        begin
            $display("\n=== Test rapid insert: %0d lần đồng %s ===", count, 
                     (coin_type == 2'b01) ? "1₫" : 
                     (coin_type == 2'b10) ? "5₫" : "10₫");
            
            for (i = 0; i < count; i = i + 1) begin
                insert_coin(coin_type, 0);
                #20; // Chờ 1 cycle để ổn định
            end
        end
    endtask
    
    // Test stimulus
    initial begin
        $display("======= KIỂM THỬ MONEY COUNTER VỚI EDGE DETECTION =======");
        $display("Testbench để verify chức năng đếm tiền chính xác");
        $display("Hỗ trợ: 1₫ (01), 5₫ (10), 10₫ (11)");
        $display("Giới hạn: Tối đa 31₫");
        
        // Initialize signals
        reset = 1;
        coin_in = 2'b00;
        
        // Reset hệ thống
        #50;
        reset = 0;
        #20;
        $display("\nTime %0t: Reset hoàn tất, tổng tiền: %0d₫", $time, total_amount);
        
        // =================== TEST CASE 1: Nhập từng loại tiền ===================
        $display("\n=== TEST CASE 1: Nhập từng loại tiền ===");
        
        insert_coin(2'b01, "1₫");  // Nhập 1₫
        #20;
        insert_coin(2'b10, "5₫");  // Nhập 5₫
        #20;
        insert_coin(2'b11, "10₫"); // Nhập 10₫
        #20;
        
        if (total_amount == 5'd16)
            $display("✅ TEST CASE 1 PASSED: 1₫ + 5₫ + 10₫ = 16₫");
        else
            $display("❌ TEST CASE 1 FAILED: Mong đợi 16₫, nhận được %0d₫", total_amount);
        
        // =================== TEST CASE 2: Nhập nhiều đồng 1₫ ===================
        reset = 1;
        #20;
        reset = 0;
        #20;
        
        rapid_insert(2'b01, 5); // Nhập 5 đồng 1₫
        
        if (total_amount == 5'd5)
            $display("✅ TEST CASE 2 PASSED: 5 × 1₫ = 5₫");
        else
            $display("❌ TEST CASE 2 FAILED: Mong đợi 5₫, nhận được %0d₫", total_amount);
        
        // =================== TEST CASE 3: Nhập nhiều đồng 5₫ ===================
        reset = 1;
        #20;
        reset = 0;
        #20;
        
        rapid_insert(2'b10, 4); // Nhập 4 đồng 5₫
        
        if (total_amount == 5'd20)
            $display("✅ TEST CASE 3 PASSED: 4 × 5₫ = 20₫");
        else
            $display("❌ TEST CASE 3 FAILED: Mong đợi 20₫, nhận được %0d₫", total_amount);
        
        // =================== TEST CASE 4: Nhập nhiều đồng 10₫ ===================
        reset = 1;
        #20;
        reset = 0;
        #20;
        
        rapid_insert(2'b11, 3); // Nhập 3 đồng 10₫
        
        if (total_amount == 5'd30)
            $display("✅ TEST CASE 4 PASSED: 3 × 10₫ = 30₫");
        else
            $display("❌ TEST CASE 4 FAILED: Mong đợi 30₫, nhận được %0d₫", total_amount);
        
        // =================== TEST CASE 5: Test overflow protection ===================
        $display("\n=== TEST CASE 5: Test overflow protection ===");
        reset = 1;
        #20;
        reset = 0;
        #20;
        
        // Nhập 31₫ (giới hạn tối đa)
        rapid_insert(2'b11, 3); // 30₫
        insert_coin(2'b01, "1₫"); // +1₫ = 31₫
        #20;
        
        if (total_amount == 5'd31)
            $display("✅ Đạt giới hạn tối đa: 31₫");
        else
            $display("❌ Lỗi giới hạn: Mong đợi 31₫, nhận được %0d₫", total_amount);
        
        // Thử nhập thêm tiền (phải bị từ chối)
        $display("Time %0t: Thử nhập thêm 1₫ khi đã đầy...", $time);
        insert_coin(2'b01, "1₫");
        #20;
        
        if (total_amount == 5'd31)
            $display("✅ TEST CASE 5 PASSED: Overflow protection hoạt động đúng");
        else
            $display("❌ TEST CASE 5 FAILED: Overflow protection lỗi, total = %0d₫", total_amount);
        
        // =================== TEST CASE 6: Test edge detection với tín hiệu giữ lâu ===================
        $display("\n=== TEST CASE 6: Test edge detection với tín hiệu giữ lâu ===");
        reset = 1;
        #20;
        reset = 0;
        #20;
        
        // Giữ tín hiệu coin_in trong nhiều cycles
        @(posedge clk);
        coin_in = 2'b00;
        @(posedge clk);
        
        coin_in = 2'b11; // Nhập 10₫
        $display("Time %0t: Bắt đầu nhập 10₫ và giữ tín hiệu trong 10 cycles", $time);
        repeat(10) @(posedge clk); // Giữ trong 10 cycles
        
        coin_in = 2'b00;
        @(posedge clk);
        
        if (total_amount == 5'd10)
            $display("✅ TEST CASE 6 PASSED: Edge detection chỉ đếm 1 lần dù giữ tín hiệu lâu");
        else
            $display("❌ TEST CASE 6 FAILED: Edge detection lỗi, total = %0d₫", total_amount);
        
        // =================== TEST CASE 7: Test sequence phức tạp ===================
        $display("\n=== TEST CASE 7: Test sequence mua sản phẩm 25₫ ===");
        reset = 1;
        #20;
        reset = 0;
        #20;
        
        // Mô phỏng mua sản phẩm 25₫
        insert_coin(2'b11, "10₫"); // 10₫
        #20;
        insert_coin(2'b11, "10₫"); // 20₫
        #20;
        insert_coin(2'b10, "5₫");  // 25₫
        #20;
        
        if (total_amount == 5'd25)
            $display("✅ TEST CASE 7 PASSED: Tích lũy đủ 25₫ để mua sản phẩm");
        else
            $display("❌ TEST CASE 7 FAILED: Mong đợi 25₫, nhận được %0d₫", total_amount);
        
        // =================== TEST CASE 8: Test reset trong quá trình hoạt động ===================
        $display("\n=== TEST CASE 8: Test reset trong quá trình hoạt động ===");
        
        insert_coin(2'b11, "10₫"); // Thêm 10₫ nữa (total = 35₫ nhưng bị giới hạn 31₫)
        #20;
        
        $display("Time %0t: Reset trong quá trình có tiền...", $time);
        reset = 1;
        #20;
        reset = 0;
        #20;
        
        if (total_amount == 5'd0)
            $display("✅ TEST CASE 8 PASSED: Reset thành công về 0₫");
        else
            $display("❌ TEST CASE 8 FAILED: Reset lỗi, total = %0d₫", total_amount);
        
        // =================== TỔNG KẾT ===================
        #50;
        $display("\n======= TỔNG KẾT KIỂM THỬ MONEY COUNTER =======");
        $display("✅ Edge Detection: Hoạt động chính xác");
        $display("✅ Overflow Protection: Giới hạn tối đa 31₫");
        $display("✅ Reset Function: Reset về 0₫");
        $display("✅ Multiple Coin Types: 1₫, 5₫, 10₫");
        $display("✅ Signal Hold Test: Chỉ đếm 1 lần khi giữ tín hiệu lâu");
        $display("🎯 MONEY COUNTER MODULE HOẠT ĐỘNG HOÀN HẢO!");
        
        #100;
        $finish;
    end
    
    // Monitor để theo dõi thay đổi
    always @(posedge clk) begin
        // Hiển thị khi có thay đổi total_amount
        if ($time > 100 && total_amount !== uut.total_amount) begin
            // Chỉ để debug nếu cần
        end
    end
    
    // Kiểm tra edge detection
    reg [1:0] prev_coin_in = 2'b00;
    reg edge_detected = 1'b0;
    
    always @(posedge clk) begin
        if ($time > 100) begin
            // Phát hiện edge detection
            if ((coin_in != 2'b00) && (prev_coin_in == 2'b00)) begin
                edge_detected = 1'b1;
                case (coin_in)
                    2'b01: $display("Time %0t: ⚡ Edge Detection: 1₫ - Total sẽ là: %0d₫", $time, total_amount + 1);
                    2'b10: $display("Time %0t: ⚡ Edge Detection: 5₫ - Total sẽ là: %0d₫", $time, total_amount + 5);
                    2'b11: $display("Time %0t: ⚡ Edge Detection: 10₫ - Total sẽ là: %0d₫", $time, total_amount + 10);
                endcase
            end else begin
                edge_detected = 1'b0;
            end
        end
        prev_coin_in <= coin_in;
    end
    
    // Monitor thay đổi total_amount
    reg [4:0] prev_total = 5'd0;
    always @(posedge clk) begin
        if (total_amount != prev_total && $time > 100) begin
            $display("Time %0t: 💰 Total amount changed: %0d₫ → %0d₫", $time, prev_total, total_amount);
            prev_total <= total_amount;
        end
    end
    
    // Safety timeout
    initial begin
        #10000; // 10us timeout
        $display("❌ TIMEOUT: Testbench chạy quá lâu!");
        $finish;
    end

endmodule

Money_counter/money_counter.vcd
$date
	Fri Jun 13 08:09:02 2025
$end
$version
	Icarus Verilog
$end
$timescale
	1s
$end
$scope module money_counter_tb $end
$var wire 5 ! total_amount [4:0] $end
$var reg 1 " clk $end
$var reg 2 # coin_in [1:0] $end
$var reg 1 $ edge_detected $end
$var reg 2 % prev_coin_in [1:0] $end
$var reg 5 & prev_total [4:0] $end
$var reg 1 ' reset $end
$scope module uut $end
$var wire 1 " clk $end
$var wire 2 ( coin_in [1:0] $end
$var wire 1 ) coin_inserted $end
$var wire 1 ' reset $end
$var parameter 5 * COIN_1 $end
$var parameter 5 + COIN_10 $end
$var parameter 5 , COIN_5 $end
$var reg 2 - coin_in_prev [1:0] $end
$var reg 5 . total_amount [4:0] $end
$upscope $end
$scope task insert_coin $end
$var reg 8 / coin_name [7:0] $end
$var reg 2 0 coin_type [1:0] $end
$upscope $end
$scope task rapid_insert $end
$var reg 2 1 coin_type [1:0] $end
$var integer 32 2 count [31:0] $end
$var integer 32 3 i [31:0] $end
$upscope $end
$upscope $end
$enddefinitions $end
$comment Show the parameter values. $end
$dumpall
b101 ,
b1010 +
b1 *
$end
#0
$dumpvars
bx 3
bx 2
bx 1
bx 0
bx /
bx .
bx -
0)
b0 (
1'
b0 &
b0 %
0$
b0 #
0"
bx !
$end
#10
b0 -
b0 !
b0 .
1"
#20
0"
#30
1"
#40
0"
#50
1"
0'
#60
0"
#70
1"
b10101011 /
b1 0
#80
0"
#90
1)
b1 #
b1 (
1"
#100
0"
#110
0)
b1 %
b1 !
b1 .
b1 -
1$
1"
#120
0"
#130
b1 &
0$
1"
#140
0"
#150
b0 %
b0 -
b0 #
b0 (
1"
#160
0"
#170
1"
#180
0"
#190
1"
b10 0
#200
0"
#210
1)
b10 #
b10 (
1"
#220
0"
#230
0)
b10 %
b110 !
b110 .
b10 -
1$
1"
#240
0"
#250
b110 &
0$
1"
#260
0"
#270
b0 %
b0 -
b0 #
b0 (
1"
#280
0"
#290
1"
#300
0"
#310
1"
b11 0
#320
0"
#330
1)
b11 #
b11 (
1"
#340
0"
#350
0)
b11 %
b10000 !
b10000 .
b11 -
1$
1"
#360
0"
#370
b10000 &
0$
1"
#380
0"
#390
b0 %
b0 -
b0 #
b0 (
1"
#400
0"
#410
1"
#420
0"
#430
b0 !
b0 .
1"
1'
#440
0"
#450
b0 &
1"
0'
#460
0"
#470
1"
b0 /
b1 0
b0 3
b101 2
b1 1
#480
0"
#490
1)
b1 #
b1 (
1"
#500
0"
#510
0)
b1 %
b1 !
b1 .
b1 -
1$
1"
#520
0"
#530
b1 &
0$
1"
#540
0"
#550
b0 %
b0 -
b0 #
b0 (
1"
#560
0"
#570
1"
#580
0"
#590
1"
b1 3
#600
0"
#610
1)
b1 #
b1 (
1"
#620
0"
#630
0)
b1 %
b10 !
b10 .
b1 -
1$
1"
#640
0"
#650
b10 &
0$
1"
#660
0"
#670
b0 %
b0 -
b0 #
b0 (
1"
#680
0"
#690
1"
#700
0"
#710
1"
b10 3
#720
0"
#730
1)
b1 #
b1 (
1"
#740
0"
#750
0)
b1 %
b11 !
b11 .
b1 -
1$
1"
#760
0"
#770
b11 &
0$
1"
#780
0"
#790
b0 %
b0 -
b0 #
b0 (
1"
#800
0"
#810
1"
#820
0"
#830
1"
b11 3
#840
0"
#850
1)
b1 #
b1 (
1"
#860
0"
#870
0)
b1 %
b100 !
b100 .
b1 -
1$
1"
#880
0"
#890
b100 &
0$
1"
#900
0"
#910
b0 %
b0 -
b0 #
b0 (
1"
#920
0"
#930
1"
#940
0"
#950
1"
b100 3
#960
0"
#970
1)
b1 #
b1 (
1"
#980
0"
#990
0)
b1 %
b101 !
b101 .
b1 -
1$
1"
#1000
0"
#1010
b101 &
0$
1"
#1020
0"
#1030
b0 %
b0 -
b0 #
b0 (
1"
#1040
0"
#1050
1"
#1060
0"
#1070
b0 !
b0 .
1"
1'
b101 3
#1080
0"
#1090
b0 &
1"
0'
#1100
0"
#1110
1"
b10 0
b0 3
b100 2
b10 1
#1120
0"
#1130
1)
b10 #
b10 (
1"
#1140
0"
#1150
0)
b10 %
b101 !
b101 .
b10 -
1$
1"
#1160
0"
#1170
b101 &
0$
1"
#1180
0"
#1190
b0 %
b0 -
b0 #
b0 (
1"
#1200
0"
#1210
1"
#1220
0"
#1230
1"
b1 3
#1240
0"
#1250
1)
b10 #
b10 (
1"
#1260
0"
#1270
0)
b10 %
b1010 !
b1010 .
b10 -
1$
1"
#1280
0"
#1290
b1010 &
0$
1"
#1300
0"
#1310
b0 %
b0 -
b0 #
b0 (
1"
#1320
0"
#1330
1"
#1340
0"
#1350
1"
b10 3
#1360
0"
#1370
1)
b10 #
b10 (
1"
#1380
0"
#1390
0)
b10 %
b1111 !
b1111 .
b10 -
1$
1"
#1400
0"
#1410
b1111 &
0$
1"
#1420
0"
#1430
b0 %
b0 -
b0 #
b0 (
1"
#1440
0"
#1450
1"
#1460
0"
#1470
1"
b11 3
#1480
0"
#1490
1)
b10 #
b10 (
1"
#1500
0"
#1510
0)
b10 %
b10100 !
b10100 .
b10 -
1$
1"
#1520
0"
#1530
b10100 &
0$
1"
#1540
0"
#1550
b0 %
b0 -
b0 #
b0 (
1"
#1560
0"
#1570
1"
#1580
0"
#1590
b0 !
b0 .
1"
1'
b100 3
#1600
0"
#1610
b0 &
1"
0'
#1620
0"
#1630
1"
b11 0
b0 3
b11 2
b11 1
#1640
0"
#1650
1)
b11 #
b11 (
1"
#1660
0"
#1670
0)
b11 %
b1010 !
b1010 .
b11 -
1$
1"
#1680
0"
#1690
b1010 &
0$
1"
#1700
0"
#1710
b0 %
b0 -
b0 #
b0 (
1"
#1720
0"
#1730
1"
#1740
0"
#1750
1"
b1 3
#1760
0"
#1770
1)
b11 #
b11 (
1"
#1780
0"
#1790
0)
b11 %
b10100 !
b10100 .
b11 -
1$
1"
#1800
0"
#1810
b10100 &
0$
1"
#1820
0"
#1830
b0 %
b0 -
b0 #
b0 (
1"
#1840
0"
#1850
1"
#1860
0"
#1870
1"
b10 3
#1880
0"
#1890
1)
b11 #
b11 (
1"
#1900
0"
#1910
0)
b11 %
b11110 !
b11110 .
b11 -
1$
1"
#1920
0"
#1930
b11110 &
0$
1"
#1940
0"
#1950
b0 %
b0 -
b0 #
b0 (
1"
#1960
0"
#1970
1"
#1980
0"
#1990
b0 !
b0 .
1"
1'
b11 3
#2000
0"
#2010
b0 &
1"
0'
#2020
0"
#2030
1"
b0 3
#2040
0"
#2050
1)
b11 #
b11 (
1"
#2060
0"
#2070
0)
b11 %
b1010 !
b1010 .
b11 -
1$
1"
#2080
0"
#2090
b1010 &
0$
1"
#2100
0"
#2110
b0 %
b0 -
b0 #
b0 (
1"
#2120
0"
#2130
1"
#2140
0"
#2150
1"
b1 3
#2160
0"
#2170
1)
b11 #
b11 (
1"
#2180
0"
#2190
0)
b11 %
b10100 !
b10100 .
b11 -
1$
1"
#2200
0"
#2210
b10100 &
0$
1"
#2220
0"
#2230
b0 %
b0 -
b0 #
b0 (
1"
#2240
0"
#2250
1"
#2260
0"
#2270
1"
b10 3
#2280
0"
#2290
1)
b11 #
b11 (
1"
#2300
0"
#2310
0)
b11 %
b11110 !
b11110 .
b11 -
1$
1"
#2320
0"
#2330
b11110 &
0$
1"
#2340
0"
#2350
b0 %
b0 -
b0 #
b0 (
1"
#2360
0"
#2370
1"
#2380
0"
#2390
1"
b10101011 /
b1 0
b11 3
#2400
0"
#2410
1)
b1 #
b1 (
1"
#2420
0"
#2430
0)
b1 %
b11111 !
b11111 .
b1 -
1$
1"
#2440
0"
#2450
b11111 &
0$
1"
#2460
0"
#2470
b0 %
b0 -
b0 #
b0 (
1"
#2480
0"
#2490
1"
#2500
0"
#2510
1"
#2520
0"
#2530
1)
b1 #
b1 (
1"
#2540
0"
#2550
0)
b1 %
b1 -
1$
1"
#2560
0"
#2570
0$
1"
#2580
0"
#2590
b0 %
b0 -
b0 #
b0 (
1"
#2600
0"
#2610
1"
#2620
0"
#2630
b0 !
b0 .
1"
1'
#2640
0"
#2650
b0 &
1"
0'
#2660
0"
#2670
1"
#2680
0"
#2690
1)
b11 #
b11 (
1"
#2700
0"
#2710
0)
b11 %
b1010 !
b1010 .
b11 -
1$
1"
#2720
0"
#2730
b1010 &
0$
1"
#2740
0"
#2750
1"
#2760
0"
#2770
1"
#2780
0"
#2790
1"
#2800
0"
#2810
1"
#2820
0"
#2830
1"
#2840
0"
#2850
1"
#2860
0"
#2870
1"
#2880
0"
#2890
b0 #
b0 (
1"
#2900
0"
#2910
b0 %
b0 -
b0 !
b0 .
1'
1"
#2920
0"
#2930
b0 &
1"
0'
#2940
0"
#2950
1"
b11 0
#2960
0"
#2970
1)
b11 #
b11 (
1"
#2980
0"
#2990
0)
b11 %
b1010 !
b1010 .
b11 -
1$
1"
#3000
0"
#3010
b1010 &
0$
1"
#3020
0"
#3030
b0 %
b0 -
b0 #
b0 (
1"
#3040
0"
#3050
1"
#3060
0"
#3070
1"
#3080
0"
#3090
1)
b11 #
b11 (
1"
#3100
0"
#3110
0)
b11 %
b10100 !
b10100 .
b11 -
1$
1"
#3120
0"
#3130
b10100 &
0$
1"
#3140
0"
#3150
b0 %
b0 -
b0 #
b0 (
1"
#3160
0"
#3170
1"
#3180
0"
#3190
1"
b10 0
#3200
0"
#3210
1)
b10 #
b10 (
1"
#3220
0"
#3230
0)
b10 %
b11001 !
b11001 .
b10 -
1$
1"
#3240
0"
#3250
b11001 &
0$
1"
#3260
0"
#3270
b0 %
b0 -
b0 #
b0 (
1"
#3280
0"
#3290
1"
#3300
0"
#3310
1"
b11 0
#3320
0"
#3330
1)
b11 #
b11 (
1"
#3340
0"
#3350
0)
b11 %
b11 -
1$
1"
#3360
0"
#3370
0$
1"
#3380
0"
#3390
b0 %
b0 -
b0 #
b0 (
1"
#3400
0"
#3410
1"
#3420
0"
#3430
b0 !
b0 .
1"
1'
#3440
0"
#3450
b0 &
1"
0'
