Product_selection/Product_selection.v
module product_selection (
    input wire clk,
    input wire reset,
    input wire [1:0] product_sel,  // 00: no selection, 01: product A, 10: product B, 11: product C
    output reg [4:0] selected_price
);
    // Định nghĩa giá sản phẩm
    parameter PRODUCT_A_PRICE = 5'd15;
    parameter PRODUCT_B_PRICE = 5'd20;
    parameter PRODUCT_C_PRICE = 5'd25;
    
    always @(posedge clk or posedge reset) begin
        if (reset) begin
            selected_price <= 5'd0;
        end
        else begin
            case (product_sel)
                2'b01: selected_price <= PRODUCT_A_PRICE;
                2'b10: selected_price <= PRODUCT_B_PRICE;
                2'b11: selected_price <= PRODUCT_C_PRICE;
                default: selected_price <= selected_price; // Giữ nguyên giá trị
            endcase
        end
    end
endmodule

Product_selection/Product_selection_tb.v
module product_selection_tb;
    // Tín hiệu đầu vào
    reg clk;
    reg reset;
    reg [1:0] product_sel;
    
    // Tín hiệu đầu ra
    wire [4:0] selected_price;
    
    // Khởi tạo module kiểm tra
    product_selection uut (
        .clk(clk),
        .reset(reset),
        .product_sel(product_sel),
        .selected_price(selected_price)
    );
    
    // Tạo file VCD để xem waveform
    initial begin
        $dumpfile("product_selection_tb.vcd");
        $dumpvars(0, product_selection_tb);
    end
    
    // Tạo tín hiệu đồng hồ
    initial begin
        clk = 0;
        forever #5 clk = ~clk; // Chu kỳ đồng hồ 10ns
    end
    
    // Kịch bản kiểm tra
    initial begin
        // Khởi tạo
        reset = 1;
        product_sel = 2'b00;
        #20;
        
        // Giải phóng reset
        reset = 0;
        #10;
        
        // Kiểm tra chọn sản phẩm A (15₫)
        product_sel = 2'b01;
        #20;
        
        // Kiểm tra chọn sản phẩm B (20₫)
        product_sel = 2'b10;
        #20;
        
        // Kiểm tra chọn sản phẩm C (25₫)
        product_sel = 2'b11;
        #20;
        
        // Kiểm tra không chọn sản phẩm
        product_sel = 2'b00;
        #20;
        
        // Kiểm tra reset
        reset = 1;
        #10;
        reset = 0;
        #10;
        
        // Kiểm tra chuyển đổi giữa các sản phẩm
        product_sel = 2'b01; // Sản phẩm A
        #20;
        product_sel = 2'b11; // Sản phẩm C
        #20;
        product_sel = 2'b10; // Sản phẩm B
        #20;
        
        // Kết thúc mô phỏng
        #10;
        $finish;
    end
    
    // Giám sát và hiển thị kết quả
    initial begin
        $monitor("Time=%t, reset=%b, product_sel=%b, selected_price=%d", 
                 $time, reset, product_sel, selected_price);
    end
endmodule

Product_selection/product_selection_tb.vcd
$date
	Fri Jun 13 08:07:58 2025
$end
$version
	Icarus Verilog
$end
$timescale
	1s
$end
$scope module product_selection_tb $end
$var wire 5 ! selected_price [4:0] $end
$var reg 1 " clk $end
$var reg 2 # product_sel [1:0] $end
$var reg 1 $ reset $end
$scope module uut $end
$var wire 1 " clk $end
$var wire 2 % product_sel [1:0] $end
$var wire 1 $ reset $end
$var parameter 5 & PRODUCT_A_PRICE $end
$var parameter 5 ' PRODUCT_B_PRICE $end
$var parameter 5 ( PRODUCT_C_PRICE $end
$var reg 5 ) selected_price [4:0] $end
$upscope $end
$upscope $end
$enddefinitions $end
$comment Show the parameter values. $end
$dumpall
b11001 (
b10100 '
b1111 &
$end
#0
$dumpvars
b0 )
b0 %
1$
b0 #
0"
b0 !
$end
#5
1"
#10
0"
#15
1"
#20
0"
0$
#25
1"
#30
0"
b1 #
b1 %
#35
b1111 !
b1111 )
1"
#40
0"
#45
1"
#50
0"
b10 #
b10 %
#55
b10100 !
b10100 )
1"
#60
0"
#65
1"
#70
0"
b11 #
b11 %
#75
b11001 !
b11001 )
1"
#80
0"
#85
1"
#90
0"
b0 #
b0 %
#95
1"
#100
0"
#105
1"
#110
b0 !
b0 )
0"
1$
#115
1"
#120
0"
0$
#125
1"
#130
0"
b1 #
b1 %
#135
b1111 !
b1111 )
1"
#140
0"
#145
1"
#150
0"
b11 #
b11 %
#155
b11001 !
b11001 )
1"
#160
0"
#165
1"
#170
0"
b10 #
b10 %
#175
b10100 !
b10100 )
1"
