Change_calculator/Change_calculator.v
module Change_calculator (
    input wire clk,
    input wire reset,
    input wire [4:0] current_amount,
    input wire [4:0] product_price,
    input wire calculate,
    
    output reg [4:0] change_amount,
    output reg valid_transaction
);
    
    always @(posedge clk) begin
        if (reset) begin
            change_amount <= 5'd0;
            valid_transaction <= 1'b0;
        end
        else if (calculate) begin
            // SỬA: Logic rõ ràng hơn
            if (product_price > 5'd0 && current_amount >= product_price) begin
                // GIAO DỊCH THÀNH CÔNG - tính tiền thừa
                change_amount <= current_amount - product_price;
                valid_transaction <= 1'b1;
            end
            else begin
                // HỦY GIAO DỊCH hoặc KHÔNG ĐỦ TIỀN - trả lại toàn bộ
                change_amount <= current_amount;
                valid_transaction <= 1'b0;
            end
        end
        // SỬA: Không reset change_amount khi không calculate
        // Giữ nguyên giá trị để testbench có thể đọc được
    end
endmodule

Change_calculator/change_calculator_tb.v
module change_calculator_tb;
    // Testbench signals
    reg clk;
    reg reset;
    reg [4:0] current_amount;
    reg [4:0] product_price;
    reg calculate;
    
    wire [4:0] change_amount;
    wire valid_transaction;
    
    // Instantiate the change calculator
    change_calculator uut (
        .clk(clk),
        .reset(reset),
        .current_amount(current_amount),
        .product_price(product_price),
        .calculate(calculate),
        .change_amount(change_amount),
        .valid_transaction(valid_transaction)
    );
    
    // Clock generation - 50MHz
    initial begin
        $dumpfile("change_calculator.vcd");
        $dumpvars(0, change_calculator_tb);
        clk = 0;
        forever #10 clk = ~clk;
    end
    
    // Task để test với expected values
    task test_change;
        input [4:0] amount;
        input [4:0] price;
        input [4:0] expected_change;
        input expected_valid;
        input [200:0] test_name;
        begin
            current_amount = amount;
            product_price = price;
            calculate = 1;
            @(posedge clk);
            calculate = 0;
            @(posedge clk);
            @(posedge clk); // Chờ thêm 1 cycle để đảm bảo output ổn định
            
            if (change_amount == expected_change && valid_transaction == expected_valid) begin
                $display("✅ PASS: %s", test_name);
                $display("    %0d₫ - %0d₫ → Change: %0d₫, Valid: %b", 
                         amount, price, change_amount, valid_transaction);
            end else begin
                $display("❌ FAIL: %s", test_name);
                $display("    %0d₫ - %0d₫ → Expected: %0d₫,%b | Got: %0d₫,%b", 
                         amount, price, expected_change, expected_valid, change_amount, valid_transaction);
            end
            $display("");
        end
    endtask
    
    // Test stimulus  
    initial begin
        $display("======= KIỂM THỬ CHANGE CALCULATOR =======");
        $display("Logic: valid = (price > 0 && amount >= price)");
        $display("       change = valid ? (amount - price) : amount");
        $display("===============================================");
        
        // Initialize
        reset = 1;
        current_amount = 0;
        product_price = 0;
        calculate = 0;
        
        // Reset
        repeat(3) @(posedge clk);
        reset = 0;
        repeat(2) @(posedge clk);
        $display("Time %0t: Reset hoàn tất\n", $time);
        
        // =================== DEBUG TEST: Kiểm tra module hoạt động ===================
        $display("=== DEBUG TEST: Kiểm tra module cơ bản ===");
        
        // Test đơn giản nhất
        current_amount = 15;
        product_price = 15;
        calculate = 1;
        @(posedge clk);
        calculate = 0;
        repeat(3) @(posedge clk);
        
        $display("Debug: Amount=%0d, Price=%0d → Change=%0d, Valid=%b", 
                 15, 15, change_amount, valid_transaction);
        
        if (change_amount == 0 && valid_transaction == 1) begin
            $display("✅ Module hoạt động: 15₫ - 15₫ = 0₫, valid=1");
        end else begin
            $display("❌ Module có vấn đề: Expected change=0,valid=1 | Got change=%0d,valid=%b", 
                     change_amount, valid_transaction);
        end
        
        // Test case 2: Có tiền thừa
        current_amount = 20;
        product_price = 15;
        calculate = 1;
        @(posedge clk);
        calculate = 0;
        repeat(3) @(posedge clk);
        
        $display("Debug: Amount=%0d, Price=%0d → Change=%0d, Valid=%b", 
                 20, 15, change_amount, valid_transaction);
        
        if (change_amount == 5 && valid_transaction == 1) begin
            $display("✅ Module hoạt động: 20₫ - 15₫ = 5₫, valid=1");
        end else begin
            $display("❌ Module có vấn đề: Expected change=5,valid=1 | Got change=%0d,valid=%b", 
                     change_amount, valid_transaction);
        end
        
        // Test case 3: Không đủ tiền
        current_amount = 10;
        product_price = 15;
        calculate = 1;
        @(posedge clk);
        calculate = 0;
        repeat(3) @(posedge clk);
        
        $display("Debug: Amount=%0d, Price=%0d → Change=%0d, Valid=%b", 
                 10, 15, change_amount, valid_transaction);
        
        if (change_amount == 10 && valid_transaction == 0) begin
            $display("✅ Module hoạt động: 10₫ < 15₫ → trả 10₫, valid=0");
        end else begin
            $display("❌ Module có vấn đề: Expected change=10,valid=0 | Got change=%0d,valid=%b", 
                     change_amount, valid_transaction);
        end
        
        // Test case 4: Price = 0 (hủy giao dịch)
        current_amount = 10;
        product_price = 0;
        calculate = 1;
        @(posedge clk);
        calculate = 0;
        repeat(3) @(posedge clk);
        
        $display("Debug: Amount=%0d, Price=%0d → Change=%0d, Valid=%b", 
                 10, 0, change_amount, valid_transaction);
        
        if (change_amount == 10 && valid_transaction == 0) begin
            $display("✅ Module hoạt động: Price=0 → trả 10₫, valid=0");
        end else begin
            $display("❌ Module có vấn đề: Expected change=10,valid=0 | Got change=%0d,valid=%b", 
                     change_amount, valid_transaction);
        end
        
        $display("\n=== KẾT LUẬN DEBUG ===");
        $display("Nếu tất cả debug test PASS → change_calculator.v hoạt động đúng");
        $display("Nếu có debug test FAIL → cần kiểm tra logic trong change_calculator.v");
        
        #100;
        $finish;
    end
    
    // Monitor output changes
    always @(posedge clk) begin
        if ($time > 100 && calculate) begin
            $display("Time %0t: Calculate triggered - Amount:%0d₫, Price:%0d₫", 
                     $time, current_amount, product_price);
        end
    end
    
    // Safety timeout
    initial begin
        #2000;
        $display("✅ Testbench completed successfully");
        $finish;
    end

endmodule

Change_calculator/change_calculator.vcd
$date
	Fri Jun 13 08:10:34 2025
$end
$version
	Icarus Verilog
$end
$timescale
	1s
$end
$scope module change_calculator_tb $end
$var wire 1 ! valid_transaction $end
$var wire 5 " change_amount [4:0] $end
$var reg 1 # calculate $end
$var reg 1 $ clk $end
$var reg 5 % current_amount [4:0] $end
$var reg 5 & product_price [4:0] $end
$var reg 1 ' reset $end
$scope module uut $end
$var wire 1 # calculate $end
$var wire 1 $ clk $end
$var wire 5 ( current_amount [4:0] $end
$var wire 5 ) product_price [4:0] $end
$var wire 1 ' reset $end
$var reg 5 * change_amount [4:0] $end
$var reg 1 ! valid_transaction $end
$upscope $end
$scope task test_change $end
$var reg 5 + amount [4:0] $end
$var reg 5 , expected_change [4:0] $end
$var reg 1 - expected_valid $end
$var reg 5 . price [4:0] $end
$var reg 201 / test_name [200:0] $end
$upscope $end
$upscope $end
$enddefinitions $end
$comment Show the parameter values. $end
$dumpall
$end
#0
$dumpvars
bx /
bx .
x-
bx ,
bx +
bx *
b0 )
b0 (
1'
b0 &
b0 %
0$
0#
bx "
x!
$end
#10
0!
b0 "
b0 *
1$
#20
0$
#30
1$
#40
0$
#50
0'
1$
#60
0$
#70
1$
#80
0$
#90
1!
1#
b1111 &
b1111 )
b1111 %
b1111 (
1$
#100
0$
#110
0#
1$
#120
0$
#130
1$
#140
0$
#150
1$
#160
0$
#170
b101 "
b101 *
1#
b10100 %
b10100 (
1$
#180
0$
#190
0#
1$
#200
0$
#210
1$
#220
0$
#230
1$
#240
0$
#250
0!
b1010 "
b1010 *
1#
b1010 %
b1010 (
1$
#260
0$
#270
0#
1$
#280
0$
#290
1$
#300
0$
#310
1$
#320
0$
#330
1#
b0 &
b0 )
1$
#340
0$
#350
0#
1$
